sentry_falcon/__init__.py
sentry_falcon-0.6.0.dist-info/LICENSE
sentry_falcon-0.6.0.dist-info/METADATA
sentry_falcon-0.6.0.dist-info/WHEEL
sentry_falcon-0.6.0.dist-info/top_level.txt
sentry_falcon-0.6.0.dist-info/RECORD
