Metadata-Version: 2.1
Name: sentry-falcon
Version: 0.6.0
Summary: Falcon web framework integration for the Sentry SDK
Home-page: https://github.com/jmagnusson/sentry-falcon
Author: Jacob Magnusson
Author-email: m@jacobian.se
License: BSD
Platform: any
Classifier: Development Status :: 4 - Beta
Classifier: Intended Audience :: Developers
Classifier: License :: OSI Approved :: BSD License
Classifier: Operating System :: OS Independent
Classifier: Programming Language :: Python
Classifier: Programming Language :: Python :: 2.7
Classifier: Programming Language :: Python :: 3.5
Classifier: Programming Language :: Python :: 3.6
Classifier: Programming Language :: Python :: 3.7
Classifier: Programming Language :: Python :: 3.8
Requires-Dist: falcon
Requires-Dist: sentry-sdk
Provides-Extra: test
Requires-Dist: coverage ; extra == 'test'
Requires-Dist: isort ; extra == 'test'
Requires-Dist: flake8 ; extra == 'test'
Requires-Dist: pytest ; extra == 'test'
